holistics/__init__.py
holistics/holistics.py
holistics-0.0a11.dist-info/METADATA
holistics-0.0a11.dist-info/RECORD
holistics-0.0a11.dist-info/WHEEL
holistics-0.0a11.dist-info/top_level.txt
tests/__init__.py
tests/test_holistics.py
