Metadata-Version: 2.1
Name: holistics
Version: 0.0a11
Summary: Package to export report's data from holistics.io
Home-page: https://github.com/holistics/holistics-python
Author: Phat Vo
Author-email: phat.vo@holistics.io
License: UNKNOWN
Platform: UNKNOWN
Classifier: Programming Language :: Python :: 3
Classifier: License :: OSI Approved :: MIT License
Classifier: Operating System :: OS Independent
Requires-Python: >= 3, < 4
Requires-Dist: requests
Requires-Dist: pandas
